sliceofml/__init__.py
sliceofml/api.py
sliceofml/apikey.py
sliceofml/cli.py
sliceofml/config.py
sliceofml/display.py
sliceofml-0.2.0.dist-info/entry_points.txt
sliceofml-0.2.0.dist-info/LICENSE
sliceofml-0.2.0.dist-info/WHEEL
sliceofml-0.2.0.dist-info/METADATA
sliceofml-0.2.0.dist-info/RECORD
