Metadata-Version: 2.1
Name: sliceofml
Version: 0.2.0
Summary: Slice of ML or SOML is your little 🍰 of ML.
Author: FL33TW00D
Author-email: chris@notia.ai
Requires-Python: >=3.7,<4.0
Classifier: Programming Language :: Python :: 3
Classifier: Programming Language :: Python :: 3.10
Classifier: Programming Language :: Python :: 3.7
Classifier: Programming Language :: Python :: 3.8
Classifier: Programming Language :: Python :: 3.9
Requires-Dist: click (>=8.1.3,<9.0.0)
Requires-Dist: requests-oauthlib (>=1.3.1,<2.0.0)
Requires-Dist: rich (>=12.4.4,<13.0.0)
